{
  "project_info": {
    "project_number": "608644336193",
    "project_id": "textrecognisation-4b2d2",
    "storage_bucket": "textrecognisation-4b2d2.appspot.com"
  },
  "client": [
    {
      "client_info": {
        "mobilesdk_app_id": "1:608644336193:android:7a2522e5dbb2e17bfb54c0",
        "android_client_info": {
          "package_name": "com.example.textrecognisationapp"
        }
      },
      "oauth_client": [
        {
          "client_id": "608644336193-j1lq0br2kn0egec6msntttjijm5m6m8t.apps.googleusercontent.com",
          "client_type": 3
        }
      ],
      "api_key": [
        {
          "current_key": "AIzaSyDNw97vNeLWLfZfLrRqbVS8avnLOpJ-WMc"
        }
      ],
      "services": {
        "appinvite_service": {
          "other_platform_oauth_client": [
            {
              "client_id": "608644336193-j1lq0br2kn0egec6msntttjijm5m6m8t.apps.googleusercontent.com",
              "client_type": 3
            }
          ]
        }
      }
    }
  ],
  "configuration_version": "1"
}